defaultcc/__init__.py
defaultcc/admin.py
defaultcc/main.py
defaultcc/model.py
defaultcc/htdocs/defaultcc.js
TracDefaultCc-0.5.dist-info/COPYING
TracDefaultCc-0.5.dist-info/METADATA
TracDefaultCc-0.5.dist-info/WHEEL
TracDefaultCc-0.5.dist-info/entry_points.txt
TracDefaultCc-0.5.dist-info/top_level.txt
TracDefaultCc-0.5.dist-info/zip-safe
TracDefaultCc-0.5.dist-info/RECORD
